bilireq-0.2.13.dist-info/METADATA
bilireq-0.2.13.dist-info/WHEEL
bilireq-0.2.13.dist-info/licenses/LICENSE
bilireq/__init__.py
bilireq/_typing.py
bilireq/auth/__init__.py
bilireq/bangumi/__init__.py
bilireq/dynamic/__init__.py
bilireq/exceptions.py
bilireq/grpc/__init__.py
bilireq/grpc/dynamic/__init__.py
bilireq/grpc/live/__init__.py
bilireq/grpc/protos/bilibili/account/fission/v1/fission.proto
bilireq/grpc/protos/bilibili/account/fission/v1/fission_pb2.py
bilireq/grpc/protos/bilibili/account/fission/v1/fission_pb2.pyi
bilireq/grpc/protos/bilibili/account/fission/v1/fission_pb2_grpc.py
bilireq/grpc/protos/bilibili/ad/v1/ad.proto
bilireq/grpc/protos/bilibili/ad/v1/ad_pb2.py
bilireq/grpc/protos/bilibili/ad/v1/ad_pb2.pyi
bilireq/grpc/protos/bilibili/ad/v1/ad_pb2_grpc.py
bilireq/grpc/protos/bilibili/api/player/v1/player.proto
bilireq/grpc/protos/bilibili/api/player/v1/player_pb2.py
bilireq/grpc/protos/bilibili/api/player/v1/player_pb2.pyi
bilireq/grpc/protos/bilibili/api/player/v1/player_pb2_grpc.py
bilireq/grpc/protos/bilibili/api/probe/v1/probe.proto
bilireq/grpc/protos/bilibili/api/probe/v1/probe_pb2.py
bilireq/grpc/protos/bilibili/api/probe/v1/probe_pb2.pyi
bilireq/grpc/protos/bilibili/api/probe/v1/probe_pb2_grpc.py
bilireq/grpc/protos/bilibili/api/ticket/v1/ticket.proto
bilireq/grpc/protos/bilibili/api/ticket/v1/ticket_pb2.py
bilireq/grpc/protos/bilibili/api/ticket/v1/ticket_pb2.pyi
bilireq/grpc/protos/bilibili/api/ticket/v1/ticket_pb2_grpc.py
bilireq/grpc/protos/bilibili/app/archive/middleware/v1/preload.proto
bilireq/grpc/protos/bilibili/app/archive/middleware/v1/preload_pb2.py
bilireq/grpc/protos/bilibili/app/archive/middleware/v1/preload_pb2.pyi
bilireq/grpc/protos/bilibili/app/archive/middleware/v1/preload_pb2_grpc.py
bilireq/grpc/protos/bilibili/app/archive/v1/archive.proto
bilireq/grpc/protos/bilibili/app/archive/v1/archive_pb2.py
bilireq/grpc/protos/bilibili/app/archive/v1/archive_pb2.pyi
bilireq/grpc/protos/bilibili/app/archive/v1/archive_pb2_grpc.py
bilireq/grpc/protos/bilibili/app/card/v1/ad.proto
bilireq/grpc/protos/bilibili/app/card/v1/ad_pb2.py
bilireq-0.2.13.dist-info/RECORD
