Metadata-Version: 2.1
Name: bilireq
Version: 0.2.13
Summary: 又一个哔哩哔哩请求库
Author-Email: SK-415 <2967923486@qq.com>
License: MIT
Project-URL: Repository, https://github.com/SK-415/bilireq
Requires-Python: <4.0,>=3.8
Requires-Dist: httpx
Requires-Dist: pycryptodome>=3.19.0
Requires-Dist: grpcio>=1.56.2
Requires-Dist: protobuf>=4.23.4
Requires-Dist: qrcode>=7.4.2
Requires-Dist: lxml; extra == "web-qrcode"
Provides-Extra: web_qrcode
